vibranium_dome_sdk/__init__.py
vibranium_dome_sdk-0.1.6.dist-info/METADATA
vibranium_dome_sdk-0.1.6.dist-info/WHEEL
vibranium_dome_sdk-0.1.6.dist-info/RECORD
