Metadata-Version: 2.1
Name: vibranium-dome-sdk
Version: 0.1.6
Summary: 
Author: Uri Shamay
Author-email: cmpxchg16@gmail.com
Requires-Python: >=3.9,<4.0
Classifier: Programming Language :: Python :: 3
Classifier: Programming Language :: Python :: 3.9
Classifier: Programming Language :: Python :: 3.10
Classifier: Programming Language :: Python :: 3.11
Requires-Dist: traceloop-sdk (>=0.3.4,<0.4.0)
